llama_cpp_py/__init__.py
llama_cpp_py/logger.py
llama_cpp_py/client/__init__.py
llama_cpp_py/client/async_.py
llama_cpp_py/client/base.py
llama_cpp_py/client/sync.py
llama_cpp_py/release_manager/__init__.py
llama_cpp_py/release_manager/base.py
llama_cpp_py/release_manager/manager.py
llama_cpp_py/server/__init__.py
llama_cpp_py/server/async_.py
llama_cpp_py/server/base.py
llama_cpp_py/server/sync.py
llama_cpp_py-0.1.24.dist-info/licenses/LICENSE
llama_cpp_py-0.1.24.dist-info/METADATA
llama_cpp_py-0.1.24.dist-info/WHEEL
llama_cpp_py-0.1.24.dist-info/top_level.txt
llama_cpp_py-0.1.24.dist-info/RECORD
