Metadata-Version: 2.4
Name: llama-cpp-py
Version: 0.1.24
Summary: Python wrapper for running the llama.cpp server
Author: sergey21000
License-Expression: MIT
Project-URL: Repository, https://github.com/sergey21000/llama-cpp-py
Classifier: Programming Language :: Python :: 3
Classifier: Operating System :: OS Independent
Requires-Python: >=3.10
License-File: LICENSE
Requires-Dist: aiohttp>=3.12
Requires-Dist: requests>=2.32.4
Requires-Dist: tqdm>=4.67.1
Requires-Dist: openai>=2.5.0
Requires-Dist: python-dotenv>=1.2.1
Requires-Dist: platformdirs>=4.5.0
Requires-Dist: pillow>=11
Provides-Extra: test
Requires-Dist: pytest>=8.4.2; extra == "test"
Requires-Dist: pytest-asyncio>=1.2.0; extra == "test"
Requires-Dist: colorama>=0.4.6; extra == "test"
Dynamic: license-file
